odoo/addons/web_export_html_as_text/README.rst
odoo/addons/web_export_html_as_text/__init__.py
odoo/addons/web_export_html_as_text/__manifest__.py
odoo/addons/web_export_html_as_text/i18n/it.po
odoo/addons/web_export_html_as_text/i18n/web_export_html_as_text.pot
odoo/addons/web_export_html_as_text/models/__init__.py
odoo/addons/web_export_html_as_text/models/models.py
odoo/addons/web_export_html_as_text/readme/CONFIGURE.rst
odoo/addons/web_export_html_as_text/readme/CONTRIBUTORS.rst
odoo/addons/web_export_html_as_text/readme/DESCRIPTION.rst
odoo/addons/web_export_html_as_text/readme/ROADMAP.rst
odoo/addons/web_export_html_as_text/static/description/icon.png
odoo/addons/web_export_html_as_text/static/description/index.html
odoo/addons/web_export_html_as_text/static/src/js/export_html_to_text.esm.js
odoo/addons/web_export_html_as_text/static/src/xml/export_dialog.xml
odoo/addons/web_export_html_as_text/tests/__init__.py
odoo/addons/web_export_html_as_text/tests/test_export_html_text.py
odoo/addons/web_export_html_as_text/tests/test_models.py
odoo_addon_web_export_html_as_text-16.0.1.0.0.4.dist-info/METADATA
odoo_addon_web_export_html_as_text-16.0.1.0.0.4.dist-info/WHEEL
odoo_addon_web_export_html_as_text-16.0.1.0.0.4.dist-info/top_level.txt
odoo_addon_web_export_html_as_text-16.0.1.0.0.4.dist-info/RECORD
